setup.cfg
setup.py
moip/__init__.py
moip/moip.py
moip/response.py
moip.egg-info/PKG-INFO
moip.egg-info/SOURCES.txt
moip.egg-info/dependency_links.txt
moip.egg-info/requires.txt
moip.egg-info/top_level.txt