Metadata-Version: 1.1
Name: moip
Version: 0.1
Summary: Improved Moip integration for Python 3.
Home-page: https://github.com/sisqualis/moip
Author: Martin Jungblut Schreiner
Author-email: martin@sisqualis.com.br
License: MIT
Download-URL: https://github.com/sisqualis/moip/archive/0.1.tar.gz
Platform: UNKNOWN
